{
    "social_id": "525841465",
    "username": "xsbel",
    "fullname": "Isabelle Abreu",
    "avatar_url": "https://cdn.hypeauditor.com/img/instagram/user/525841465.jpg?w=150&till=1722470340&sign=e6ee3eb4cc0cbd94f85334b960461391",
    "is_verified": true,
    "audience_geo_country_1_code": "br",
    "audience_geo_country_1_prc": 77.15,
    "blogger_thematics": [
        1027,
        1036,
        1041
    ],
    "subscribers_count": 3356668,
    "engagement_avg": 493169,
    "authentic_engagement": 337451
}