{
    "social_id": "1192899491",
    "username": "fortnite",
    "fullname": "Fortnite",
    "avatar_url": "https://cdn.hypeauditor.com/img/instagram/user/1192899491.jpg?w=150&till=1722470340&sign=068690f0691d92ba750b14c85c118ffa",
    "is_verified": true,
    "audience_geo_country_1_code": "us",
    "audience_geo_country_1_prc": 23.09,
    "blogger_thematics": [
        1049,
        1034
    ],
    "subscribers_count": 26063747,
    "engagement_avg": 131969,
    "authentic_engagement": 106821
}