{
  "basic": {
    "social_type": 3,
    "social_id": "7026127306755605509",
    "username": "amipx_",
    "fullname": "amipx_",
    "description": "\ud835\ude86\ud835\ude74\ud835\ude7b\ud835\ude72\ud835\ude7e\ud835\ude7c\ud835\ude74!! \u0e05^\u2022\ufecc\u2022^\u0e05\n\ud835\ude78\ud835\ude7d\ud835\ude83\ud835\ude79\n\ud835\ude78 \ud835\ude7b\ud835\ude7e\ud835\ude85\ud835\ude74 \ud835\ude7c\ud835\ude88 \ud835\ude7c\ud835\ude7e\ud835\ude7e\ud835\ude83\ud835\ude82\u2665\ufe0e\n\ud83c\udde7\ud83c\uddf7",
    "tier": 140,
    "is_public": true,
    "is_verified": false,
    "visibility_flags": 1,
    "avatar_url": "https://p16-va-tiktok.ibyteimg.com/tos-maliva-avt-0068/6a4efa2e7e2d5b3951fc35b994edf4f8~c5_720x720.jpeg",
    "last_media_time": "2024-05-30",
    "report_version": "2020-08-17",
    "report_updated": "2024-06-04",
    "report_data_updated": "2023-08-17",
    "report_base_updated": "2024-06-02",
    "report_state": "READY",
    "report_quality": "FULL"
  },
  "metrics": {
    "subscribers_count": {
      "value": 150993
    },
    "hs_value": {
      "value": 429.404972
    },
    "er": {
      "performance": {
        "30d": {
          "value": 24.17,
          "mark": "excellent",
          "mark_title": "EXCELLENT",
          "similar": 5.822159,
          "similar_min": 4.9468,
          "similar_max": 6.826802,
          "value_prev": 20.87
        }
      }
    },
    "views_avg": {
      "performance": {
        "30d": {
          "value": 94793
        }
      }
    },
    "alikes_avg": {
      "performance": {
        "30d": {
          "value": 29588
        }
      }
    },
    "comments_avg": {
      "performance": {
        "30d": {
          "value": 142
        }
      }
    },
    "shares_avg": {
      "performance": {
        "30d": {
          "value": 1389
        }
      }
    },
    "media_count": {
      "performance": {
        "30d": {
          "value": 7
        }
      }
    }
  },
  "features": {
    "aqs": {
      "data": {
        "value": 86,
        "mark": "very_good",
        "mark_title": "VERY_GOOD",
        "description": {
          "er": {
            "mark": "excellent",
            "description": {
              "title": {
                "key": "EXCL_ER",
                "text": "Excellent audience engagement"
              }
            }
          },
          "comments_likes_ratio": {
            "mark": "good",
            "description": {
              "title": {
                "key": "GOOD_CL_RATIO",
                "text": "Good comments to likes ratio"
              }
            }
          },
          "account_growth": {
            "mark": "excellent",
            "description": {
              "title": {
                "key": "EXCL_GROWTH",
                "text": "Excellent account growth rate"
              }
            }
          }
        }
      }
    },
    "blogger_geo": {
      "data": {
        "country": "br"
      }
    }
  },
  "_number": 623,
  "_delta": null
}