{
  "basic": {
    "social_type": 3,
    "social_id": "6833460568005166085",
    "username": "yollaraujo",
    "fullname": "yolla",
    "description": "\ud83d\udc8c yolla@wupper.com.br\n\n\ud83d\udc05",
    "tier": 147,
    "is_public": true,
    "is_verified": false,
    "visibility_flags": 1,
    "avatar_url": "https://p16-va-tiktok.ibyteimg.com/tos-maliva-avt-0068/630c1a20b0f2d1e8feabbe51fdfc1c5f~c5_720x720.jpeg",
    "last_media_time": "2024-06-02",
    "report_version": "2020-08-17",
    "report_updated": "2024-06-06",
    "report_data_updated": "2023-12-29",
    "report_base_updated": "2024-06-06",
    "report_state": "READY",
    "report_quality": "FULL"
  },
  "metrics": {
    "subscribers_count": {
      "value": 1648327
    },
    "hs_value": {
      "value": 2033.914351
    },
    "er": {
      "performance": {
        "30d": {
          "value": 16.21,
          "mark": "excellent",
          "mark_title": "EXCELLENT",
          "similar": 6.117799,
          "similar_min": 5.299669,
          "similar_max": 7.083806,
          "value_prev": 15.45
        }
      }
    },
    "views_avg": {
      "performance": {
        "30d": {
          "value": 560758
        }
      }
    },
    "alikes_avg": {
      "performance": {
        "30d": {
          "value": 81691
        }
      }
    },
    "comments_avg": {
      "performance": {
        "30d": {
          "value": 226
        }
      }
    },
    "shares_avg": {
      "performance": {
        "30d": {
          "value": 218
        }
      }
    },
    "media_count": {
      "performance": {
        "30d": {
          "value": 16
        }
      }
    }
  },
  "features": {
    "aqs": {
      "data": {
        "value": 80,
        "prc_better": 96,
        "mark": "very_good",
        "mark_title": "VERY_GOOD",
        "description": {
          "er": {
            "mark": "excellent",
            "description": {
              "title": {
                "key": "EXCL_ER",
                "text": "Excellent audience engagement"
              }
            }
          },
          "comments_likes_ratio": {
            "mark": "average",
            "description": {
              "title": {
                "key": "AVG_CL_RATIO",
                "text": "Average comments to likes ratio"
              }
            }
          },
          "account_growth": {
            "mark": "excellent",
            "description": {
              "title": {
                "key": "EXCL_GROWTH",
                "text": "Excellent account growth rate"
              }
            }
          }
        }
      }
    },
    "blogger_geo": {
      "data": {
        "country": "br"
      }
    }
  },
  "_number": 342,
  "_delta": null
}