{
  "basic": {
    "social_type": 3,
    "social_id": "6806481279644271621",
    "username": "theodoro_fs",
    "fullname": "Theodoro",
    "description": "Segue l\u00e1 no insta: @theodoro",
    "tier": 147,
    "is_public": true,
    "is_verified": false,
    "visibility_flags": 1,
    "avatar_url": "https://p16-va-tiktok.ibyteimg.com/tos-maliva-avt-0068/5b37c9ddda07970eee507a3a6790913e~c5_720x720.jpeg",
    "last_media_time": "2024-06-05",
    "report_version": "2020-08-17",
    "report_updated": "2024-06-06",
    "report_data_updated": "2024-02-03",
    "report_base_updated": "2024-06-06",
    "report_state": "READY",
    "report_quality": "FULL"
  },
  "metrics": {
    "subscribers_count": {
      "value": 1830260
    },
    "hs_value": {
      "value": 479.695707
    },
    "er": {
      "performance": {
        "30d": {
          "value": 11.7,
          "mark": "very_good",
          "mark_title": "VERY_GOOD",
          "similar": 6.117799,
          "similar_min": 5.299669,
          "similar_max": 7.083806,
          "value_prev": 11.21
        }
      }
    },
    "views_avg": {
      "performance": {
        "30d": {
          "value": 228796
        }
      }
    },
    "alikes_avg": {
      "performance": {
        "30d": {
          "value": 24436
        }
      }
    },
    "comments_avg": {
      "performance": {
        "30d": {
          "value": 398
        }
      }
    },
    "shares_avg": {
      "performance": {
        "30d": {
          "value": 460
        }
      }
    },
    "media_count": {
      "performance": {
        "30d": {
          "value": 32
        }
      }
    }
  },
  "features": {
    "aqs": {
      "data": {
        "value": 94,
        "prc_better": 99,
        "mark": "excellent",
        "mark_title": "EXCELLENT",
        "description": {
          "er": {
            "mark": "excellent",
            "description": {
              "title": {
                "key": "EXCL_ER",
                "text": "Excellent audience engagement"
              }
            }
          },
          "comments_likes_ratio": {
            "mark": "excellent",
            "description": {
              "title": {
                "key": "EXCL_CL_RATIO",
                "text": "Excellent comments to likes ratio"
              }
            }
          },
          "account_growth": {
            "mark": "excellent",
            "description": {
              "title": {
                "key": "EXCL_GROWTH",
                "text": "Excellent account growth rate"
              }
            }
          }
        }
      }
    },
    "blogger_geo": {
      "data": {
        "country": "br"
      }
    }
  },
  "_number": 605,
  "_delta": null
}