{
  "basic": {
    "social_type": 3,
    "social_id": "6516520094883910656",
    "username": "sofiaespanha",
    "fullname": "sofia espanha",
    "description": "powered by @furia\n\ncontato sofiaespanhacomercial@gmail.com",
    "tier": 147,
    "is_public": true,
    "is_verified": true,
    "visibility_flags": 1,
    "avatar_url": "https://p16-va-tiktok.ibyteimg.com/tos-maliva-avt-0068/17c370f4669224ce83e9a26b8f38acb1~c5_720x720.jpeg",
    "last_media_time": "2024-06-05",
    "report_version": "2020-08-17",
    "report_updated": "2024-06-05",
    "report_data_updated": "2022-10-17",
    "report_base_updated": "2024-06-05",
    "report_state": "READY",
    "report_quality": "FULL"
  },
  "metrics": {
    "subscribers_count": {
      "value": 6778815
    },
    "hs_value": {
      "value": 94640.04326
    },
    "er": {
      "performance": {
        "30d": {
          "value": 12.34,
          "mark": "excellent",
          "mark_title": "EXCELLENT",
          "similar": 6.117799,
          "similar_min": 5.299669,
          "similar_max": 7.083806,
          "value_prev": 14.5
        }
      }
    },
    "views_avg": {
      "performance": {
        "30d": {
          "value": 1332608
        }
      }
    },
    "alikes_avg": {
      "performance": {
        "30d": {
          "value": 158914
        }
      }
    },
    "comments_avg": {
      "performance": {
        "30d": {
          "value": 1423
        }
      }
    },
    "shares_avg": {
      "performance": {
        "30d": {
          "value": 3046
        }
      }
    },
    "media_count": {
      "performance": {
        "30d": {
          "value": 10
        }
      }
    }
  },
  "features": {
    "aqs": {
      "data": {
        "value": 80,
        "prc_better": 96,
        "mark": "very_good",
        "mark_title": "VERY_GOOD",
        "description": {
          "er": {
            "mark": "excellent",
            "description": {
              "title": {
                "key": "EXCL_ER",
                "text": "Excellent audience engagement"
              }
            }
          },
          "comments_likes_ratio": {
            "mark": "average",
            "description": {
              "title": {
                "key": "AVG_CL_RATIO",
                "text": "Average comments to likes ratio"
              }
            }
          },
          "account_growth": {
            "mark": "excellent",
            "description": {
              "title": {
                "key": "EXCL_GROWTH",
                "text": "Excellent account growth rate"
              }
            }
          }
        }
      }
    },
    "blogger_geo": {
      "data": {
        "country": "br"
      }
    }
  },
  "_number": 42,
  "_delta": null
}