{
  "_number": 878,
  "_delta": null,
  "basic": {
    "id": null,
    "social_id": "UC-lB2nyJ4lZXTgFoJ8bxh0A",
    "username": "jesus_copy",
    "title": null,
    "fullname": "JesusCopy",
    "avatar_url": "https://yt3.googleusercontent.com/CpcJxo8rlbNV7eWDmEuONuUM2iJJYrn2zIL5Dw_7cjKPrtq50SVNSgiPR9ZdE2ea4AJn_Q0=s900-c-k-c0x00ffffff-no-rj",
    "is_verified": false
  },
  "features": {
    "audience_geo_country_1_code": "br",
    "audience_geo_country_1_prc": 95.38,
    "audience_geo": {
      "data": {
        "countries": [
          {
            "id": "br",
            "code": null,
            "prc": 95.38,
            "hs_value": 0.584404
          },
          {
            "id": "pt",
            "code": null,
            "prc": 1.23,
            "hs_value": null
          },
          {
            "id": "us",
            "code": null,
            "prc": 1.13,
            "hs_value": null
          },
          {
            "id": "ao",
            "code": null,
            "prc": 0.38,
            "hs_value": null
          },
          {
            "id": "it",
            "code": null,
            "prc": 0.38,
            "hs_value": null
          }
        ]
      }
    },
    "blogger_thematics": {
      "data": [
        6
      ]
    }
  },
  "metrics": {
    "subscribers_count": {
      "value": 2315078
    },
    "comments_avg": {
      "performance": {
        "30d": {
          "value": 115
        }
      }
    },
    "likes_avg": {
      "performance": {
        "30d": {
          "value": 2607
        }
      }
    },
    "engagement_avg": {
      "performance": {
        "30d": {
          "value": 2722
        }
      }
    },
    "video_views_avg": {
      "performance": {
        "30d": {
          "value": 20379
        }
      }
    }
  }
}